MANIFEST.in
README.md
setup.py
nmd/__init__.py
nmd/main.py
nmd/nl_mqtt.py
nmd/nl_sensors.py
nmd/nl_serial.py
nmd/utils.py
nmd/systemd_script/create_service.sh
nmd/systemd_script/noolite_mtrf_mqtt.service
noolite_mtrf_mqtt.egg-info/PKG-INFO
noolite_mtrf_mqtt.egg-info/SOURCES.txt
noolite_mtrf_mqtt.egg-info/dependency_links.txt
noolite_mtrf_mqtt.egg-info/entry_points.txt
noolite_mtrf_mqtt.egg-info/requires.txt
noolite_mtrf_mqtt.egg-info/top_level.txt