Metadata-Version: 1.0
Name: noolite-mtrf-mqtt
Version: 0.1.3
Summary: NooLite MTRF serial port to MQTT messages
Home-page: https://bitbucket.org/AlekseevAV/noolite-mtrf-to-mqtt
Author: UNKNOWN
Author-email: UNKNOWN
License: UNKNOWN
Platform: UNKNOWN
